{
	"gradeData": [
{"grade":"1","wave":"1","hp":"160","gold":"24","num":[0,0,2],"mission":"1"},
{"grade":"1","wave":"2","hp":"200","gold":"24","num":[0,0,3],"mission":"2"},
{"grade":"1","wave":"3","hp":"1750","gold":"31","num":[1],"mission":"2"},
{"grade":"2","wave":"1","hp":"1100","gold":"35","num":[0,0,4],"mission":"2"},
{"grade":"2","wave":"2","hp":"1600","gold":"40","num":[0,0,4],"mission":"2"},
{"grade":"2","wave":"3","hp":"2040","gold":"40","num":[0,0,4],"mission":"2"},
{"grade":"2","wave":"4","hp":"12500","gold":"51","num":[1],"mission":"2"},
{"grade":"3","wave":"1","hp":"3000","gold":"55","num":[0,0,4],"mission":"3"},
{"grade":"3","wave":"2","hp":"3750","gold":"60","num":[0,0,4],"mission":"3"},
{"grade":"3","wave":"3","hp":"3900","gold":"65","num":[0,0,4],"mission":"3"},
{"grade":"3","wave":"4","hp":"4100","gold":"75","num":[0,0,4],"mission":"3"},
{"grade":"3","wave":"5","hp":"20900","gold":"88","num":[1],"mission":"3"},
{"grade":"4","wave":"1","hp":"4600","gold":"96","num":[2,2,1],"mission":"3"},
{"grade":"4","wave":"2","hp":"4900","gold":"102","num":[2,2,1],"mission":"3"},
{"grade":"4","wave":"3","hp":"5240","gold":"114","num":[2,2,1],"mission":"3"},
{"grade":"4","wave":"4","hp":"6050","gold":"126","num":[2,2,1],"mission":"3"},
{"grade":"4","wave":"5","hp":"7100","gold":"144","num":[2,2,1],"mission":"3"},
{"grade":"4","wave":"6","hp":"33900","gold":"166","num":[1],"mission":"3"},
{"grade":"5","wave":"1","hp":"6050","gold":"182","num":[2,3,1],"mission":"4"},
{"grade":"5","wave":"2","hp":"6454","gold":"203","num":[2,3,1],"mission":"4"},
{"grade":"5","wave":"3","hp":"6617","gold":"224","num":[2,3,1],"mission":"4"},
{"grade":"5","wave":"4","hp":"6940","gold":"245","num":[2,3,1],"mission":"4"},
{"grade":"5","wave":"5","hp":"8390","gold":"273","num":[2,3,1],"mission":"4"},
{"grade":"5","wave":"6","hp":"9190","gold":"301","num":[2,3,1],"mission":"4"},
{"grade":"5","wave":"7","hp":"54876","gold":"335","num":[1],"mission":"4"},
{"grade":"6","wave":"1","hp":"8877","gold":"368","num":[2,3,2],"mission":"4"},
{"grade":"6","wave":"2","hp":"9361","gold":"408","num":[2,3,2],"mission":"4"},
{"grade":"6","wave":"3","hp":"9845","gold":"448","num":[2,3,2],"mission":"4"},
{"grade":"6","wave":"4","hp":"10652","gold":"496","num":[2,3,2],"mission":"4"},
{"grade":"6","wave":"5","hp":"12000","gold":"552","num":[2,3,2],"mission":"4"},
{"grade":"6","wave":"6","hp":"12990","gold":"608","num":[2,3,2],"mission":"4"},
{"grade":"6","wave":"7","hp":"96800","gold":"674","num":[1],"mission":"4"},
{"grade":"7","wave":"1","hp":"16500","gold":"744","num":[2,3,2],"mission":"5"},
{"grade":"7","wave":"2","hp":"18000","gold":"856","num":[2,3,2],"mission":"5"},
{"grade":"7","wave":"3","hp":"20700","gold":"944","num":[2,3,2],"mission":"5"},
{"grade":"7","wave":"4","hp":"23800","gold":"1047","num":[2,3,2],"mission":"5"},
{"grade":"7","wave":"5","hp":"27000","gold":"1163","num":[2,3,2],"mission":"5"},
{"grade":"7","wave":"6","hp":"30900","gold":"1291","num":[2,3,2],"mission":"5"},
{"grade":"7","wave":"7","hp":"245752","gold":"1433","num":[1],"mission":"5"},
{"grade":"8","wave":"1","hp":"36500","gold":"1590","num":[3,3,2],"mission":"5"},
{"grade":"8","wave":"2","hp":"37500","gold":"1765","num":[3,3,2],"mission":"5"},
{"grade":"8","wave":"3","hp":"38500","gold":"1959","num":[3,3,2],"mission":"5"},
{"grade":"8","wave":"4","hp":"44000","gold":"2175","num":[3,3,2],"mission":"5"},
{"grade":"8","wave":"5","hp":"52500","gold":"2414","num":[3,3,2],"mission":"5"},
{"grade":"8","wave":"6","hp":"54900","gold":"2680","num":[3,3,2],"mission":"5"},
{"grade":"8","wave":"7","hp":"486270","gold":"2975","num":[1],"mission":"5"},
{"grade":"9","wave":"1","hp":"68400","gold":"3302","num":[3,3,2],"mission":"6"},
{"grade":"9","wave":"2","hp":"71000","gold":"3665","num":[3,3,2],"mission":"6"},
{"grade":"9","wave":"3","hp":"71500","gold":"4069","num":[3,3,2],"mission":"6"},
{"grade":"9","wave":"4","hp":"72000","gold":"4516","num":[3,3,2],"mission":"6"},
{"grade":"9","wave":"5","hp":"75600","gold":"5013","num":[3,3,2],"mission":"6"},
{"grade":"9","wave":"6","hp":"77400","gold":"5564","num":[3,3,2],"mission":"6"},
{"grade":"9","wave":"7","hp":"648360","gold":"6177","num":[1],"mission":"6"},
{"grade":"10","wave":"1","hp":"85500","gold":"6856","num":[4,3,2],"mission":"6"},
{"grade":"10","wave":"2","hp":"91800","gold":"7610","num":[4,3,2],"mission":"6"},
{"grade":"10","wave":"3","hp":"91800","gold":"8448","num":[4,3,2],"mission":"6"},
{"grade":"10","wave":"4","hp":"95400","gold":"9377","num":[4,3,2],"mission":"6"},
{"grade":"10","wave":"5","hp":"109800","gold":"10408","num":[4,3,2],"mission":"6"},
{"grade":"10","wave":"6","hp":"113400","gold":"11553","num":[4,3,2],"mission":"6"},
{"grade":"10","wave":"7","hp":"1044580","gold":"12824","num":[1],"mission":"6"},
{"grade":"11","wave":"1","hp":"135000","gold":"14235","num":[4,3,2],"mission":"7"},
{"grade":"11","wave":"2","hp":"149100","gold":"15801","num":[4,3,2],"mission":"7"},
{"grade":"11","wave":"3","hp":"156700","gold":"17539","num":[4,3,2],"mission":"7"},
{"grade":"11","wave":"4","hp":"160500","gold":"19468","num":[4,3,2],"mission":"7"},
{"grade":"11","wave":"5","hp":"177800","gold":"21610","num":[4,3,2],"mission":"7"},
{"grade":"11","wave":"6","hp":"191100","gold":"23987","num":[4,3,2],"mission":"7"},
{"grade":"11","wave":"7","hp":"1644200","gold":"26626","num":[1],"mission":"7"},
{"grade":"12","wave":"1","hp":"221700","gold":"29554","num":[4,3,2],"mission":"8"},
{"grade":"12","wave":"2","hp":"248553","gold":"32805","num":[4,3,2],"mission":"8"},
{"grade":"12","wave":"3","hp":"311640","gold":"36414","num":[4,3,2],"mission":"8"},
{"grade":"12","wave":"4","hp":"344000","gold":"40420","num":[4,3,2],"mission":"8"},
{"grade":"12","wave":"5","hp":"390000","gold":"44866","num":[4,3,2],"mission":"8"},
{"grade":"12","wave":"6","hp":"458800","gold":"49801","num":[4,3,2],"mission":"8"},
{"grade":"12","wave":"7","hp":"4083450","gold":"55280","num":[1],"mission":"8"},
{"grade":"13","wave":"1","hp":"530840","gold":"61360","num":[4,3,2],"mission":"9"},
{"grade":"13","wave":"2","hp":"588000","gold":"68110","num":[4,3,2],"mission":"9"},
{"grade":"13","wave":"3","hp":"694180","gold":"75602","num":[4,3,2],"mission":"9"},
{"grade":"13","wave":"4","hp":"776000","gold":"83918","num":[4,3,2],"mission":"9"},
{"grade":"13","wave":"5","hp":"849720","gold":"93150","num":[4,3,2],"mission":"9"},
{"grade":"13","wave":"6","hp":"930443","gold":"103396","num":[4,3,2],"mission":"9"},
{"grade":"13","wave":"7","hp":"9169519","gold":"114770","num":[1],"mission":"9"},
{"grade":"14","wave":"1","hp":"1115624","gold":"127394","num":[4,3,2],"mission":"10"},
{"grade":"14","wave":"2","hp":"1221609","gold":"141408","num":[4,3,2],"mission":"10"},
{"grade":"14","wave":"3","hp":"1337662","gold":"156963","num":[4,3,2],"mission":"10"},
{"grade":"14","wave":"4","hp":"1464740","gold":"174229","num":[4,3,2],"mission":"10"},
{"grade":"14","wave":"5","hp":"1603890","gold":"193394","num":[4,3,2],"mission":"10"},
{"grade":"14","wave":"6","hp":"1756259","gold":"214667","num":[4,3,2],"mission":"10"},
{"grade":"14","wave":"7","hp":"17307941","gold":"238281","num":[1],"mission":"10"}
]
}

